androidx_2_androidy/__init__.py
androidx_2_androidy/convert_androidy.py
convertandroidy-1.0.1.dist-info/LICENSE
convertandroidy-1.0.1.dist-info/METADATA
convertandroidy-1.0.1.dist-info/WHEEL
convertandroidy-1.0.1.dist-info/entry_points.txt
convertandroidy-1.0.1.dist-info/top_level.txt
convertandroidy-1.0.1.dist-info/RECORD
